{"descendant_id":"101000019","descendant_name":"얼티밋 버니","descendant_image_url":"https://open.api.nexon.com/static/tfd/img/6e2fca758ab68d2c59bfc2f75844d6a6","descendant_stat":[{"level":1,"stat_detail":[{"stat_id":"105000001","stat_value":98},{"stat_id":"105000025","stat_value":51},{"stat_id":"105000024","stat_value":160},{"stat_id":"105000029","stat_value":156},{"stat_id":"105000102","stat_value":0.46},{"stat_id":"105000105","stat_value":0.38}]},{"level":2,"stat_detail":[{"stat_id":"105000001","stat_value":100},{"stat_id":"105000025","stat_value":52},{"stat_id":"105000024","stat_value":161},{"stat_id":"105000029","stat_value":158},{"stat_id":"105000102","stat_value":0.46},{"stat_id":"105000105","stat_value":0.38}]},{"level":3,"stat_detail":[{"stat_id":"105000001","stat_value":103},{"stat_id":"105000025","stat_value":53},{"stat_id":"105000024","stat_value":163},{"stat_id":"105000029","stat_value":162},{"stat_id":"105000102","stat_value":0.46},{"stat_id":"105000105","stat_value":0.38}]},{"level":4,"stat_detail":[{"stat_id":"105000001","stat_value":107},{"stat_id":"105000025","stat_value":55},{"stat_id":"105000024","stat_value":164},{"stat_id":"105000029","stat_value":168},{"stat_id":"105000102","stat_value":0.48},{"stat_id":"105000105","stat_value":0.4}]},{"level":5,"stat_detail":[{"stat_id":"105000001","stat_value":112},{"stat_id":"105000025","stat_value":58},{"stat_id":"105000024","stat_value":166},{"stat_id":"105000029","stat_value":176},{"stat_id":"105000102","stat_value":0.53},{"stat_id":"105000105","stat_value":0.44}]},{"level":6,"stat_detail":[{"stat_id":"105000001","stat_value":118},{"stat_id":"105000025","stat_value":61},{"stat_id":"105000024","stat_value":167},{"stat_id":"105000029","stat_value":186},{"stat_id":"105000102","stat_value":0.55},{"stat_id":"105000105","stat_value":0.46}]},{"level":7,"stat_detail":[{"stat_id":"105000001","stat_value":126},{"stat_id":"105000025","stat_value":64},{"stat_id":"105000024","stat_value":169},{"stat_id":"105000029","stat_value":198},{"stat_id":"105000102","stat_value":0.6},{"stat_id":"105000105","stat_value":0.5}]},{"level":8,"stat_detail":[{"stat_id":"105000001","stat_value":135},{"stat_id":"105000025","stat_value":69},{"stat_id":"105000024","stat_value":170},{"stat_id":"105000029","stat_value":211},{"stat_id":"105000102","stat_value":0.65},{"stat_id":"105000105","stat_value":0.54}]},{"level":9,"stat_detail":[{"stat_id":"105000001","stat_value":145},{"stat_id":"105000025","stat_value":73},{"stat_id":"105000024","stat_value":172},{"stat_id":"105000029","stat_value":226},{"stat_id":"105000102","stat_value":0.7},{"stat_id":"105000105","stat_value":0.58}]},{"level":10,"stat_detail":[{"stat_id":"105000001","stat_value":155},{"stat_id":"105000025","stat_value":77},{"stat_id":"105000024","stat_value":173},{"stat_id":"105000029","stat_value":242},{"stat_id":"105000102","stat_value":0.74},{"stat_id":"105000105","stat_value":0.62}]},{"level":11,"stat_detail":[{"stat_id":"105000001","stat_value":166},{"stat_id":"105000025","stat_value":82},{"stat_id":"105000024","stat_value":175},{"stat_id":"105000029","stat_value":262},{"stat_id":"105000102","stat_value":0.82},{"stat_id":"105000105","stat_value":0.68}]},{"level":12,"stat_detail":[{"stat_id":"105000001","stat_value":178},{"stat_id":"105000025","stat_value":89},{"stat_id":"105000024","stat_value":177},{"stat_id":"105000029","stat_value":295},{"stat_id":"105000102","stat_value":0.86},{"stat_id":"105000105","stat_value":0.72}]},{"level":13,"stat_detail":[{"stat_id":"105000001","stat_value":192},{"stat_id":"105000025","stat_value":95},{"stat_id":"105000024","stat_value":180},{"stat_id":"105000029","stat_value":327},{"stat_id":"105000102","stat_value":0.94},{"stat_id":"105000105","stat_value":0.78}]},{"level":14,"stat_detail":[{"stat_id":"105000001","stat_value":209},{"stat_id":"105000025","stat_value":104},{"stat_id":"105000024","stat_value":183},{"stat_id":"105000029","stat_value":361},{"stat_id":"105000102","stat_value":1.03},{"stat_id":"105000105","stat_value":0.86}]},{"level":15,"stat_detail":[{"stat_id":"105000001","stat_value":224},{"stat_id":"105000025","stat_value":111},{"stat_id":"105000024","stat_value":186},{"stat_id":"105000029","stat_value":395},{"stat_id":"105000102","stat_value":1.08},{"stat_id":"105000105","stat_value":0.9}]},{"level":16,"stat_detail":[{"stat_id":"105000001","stat_value":241},{"stat_id":"105000025","stat_value":120},{"stat_id":"105000024","stat_value":189},{"stat_id":"105000029","stat_value":432},{"stat_id":"105000102","stat_value":1.18},{"stat_id":"105000105","stat_value":0.98}]},{"level":17,"stat_detail":[{"stat_id":"105000001","stat_value":258},{"stat_id":"105000025","stat_value":128},{"stat_id":"105000024","stat_value":192},{"stat_id":"105000029","stat_value":471},{"stat_id":"105000102","stat_value":1.25},{"stat_id":"105000105","stat_value":1.04}]},{"level":18,"stat_detail":[{"stat_id":"105000001","stat_value":275},{"stat_id":"105000025","stat_value":137},{"stat_id":"105000024","stat_value":195},{"stat_id":"105000029","stat_value":511},{"stat_id":"105000102","stat_value":1.34},{"stat_id":"105000105","stat_value":1.12}]},{"level":19,"stat_detail":[{"stat_id":"105000001","stat_value":295},{"stat_id":"105000025","stat_value":146},{"stat_id":"105000024","stat_value":198},{"stat_id":"105000029","stat_value":552},{"stat_id":"105000102","stat_value":1.44},{"stat_id":"105000105","stat_value":1.2}]},{"level":20,"stat_detail":[{"stat_id":"105000001","stat_value":312},{"stat_id":"105000025","stat_value":156},{"stat_id":"105000024","stat_value":201},{"stat_id":"105000029","stat_value":595},{"stat_id":"105000102","stat_value":1.54},{"stat_id":"105000105","stat_value":1.28}]},{"level":21,"stat_detail":[{"stat_id":"105000001","stat_value":332},{"stat_id":"105000025","stat_value":165},{"stat_id":"105000024","stat_value":204},{"stat_id":"105000029","stat_value":640},{"stat_id":"105000102","stat_value":1.63},{"stat_id":"105000105","stat_value":1.36}]},{"level":22,"stat_detail":[{"stat_id":"105000001","stat_value":352},{"stat_id":"105000025","stat_value":175},{"stat_id":"105000024","stat_value":208},{"stat_id":"105000029","stat_value":685},{"stat_id":"105000102","stat_value":1.73},{"stat_id":"105000105","stat_value":1.44}]},{"level":23,"stat_detail":[{"stat_id":"105000001","stat_value":372},{"stat_id":"105000025","stat_value":186},{"stat_id":"105000024","stat_value":212},{"stat_id":"105000029","stat_value":733},{"stat_id":"105000102","stat_value":1.82},{"stat_id":"105000105","stat_value":1.52}]},{"level":24,"stat_detail":[{"stat_id":"105000001","stat_value":398},{"stat_id":"105000025","stat_value":198},{"stat_id":"105000024","stat_value":217},{"stat_id":"105000029","stat_value":783},{"stat_id":"105000102","stat_value":1.94},{"stat_id":"105000105","stat_value":1.62}]},{"level":25,"stat_detail":[{"stat_id":"105000001","stat_value":418},{"stat_id":"105000025","stat_value":208},{"stat_id":"105000024","stat_value":221},{"stat_id":"105000029","stat_value":832},{"stat_id":"105000102","stat_value":2.04},{"stat_id":"105000105","stat_value":1.7}]},{"level":26,"stat_detail":[{"stat_id":"105000001","stat_value":441},{"stat_id":"105000025","stat_value":220},{"stat_id":"105000024","stat_value":225},{"stat_id":"105000029","stat_value":884},{"stat_id":"105000102","stat_value":2.16},{"stat_id":"105000105","stat_value":1.8}]},{"level":27,"stat_detail":[{"stat_id":"105000001","stat_value":464},{"stat_id":"105000025","stat_value":231},{"stat_id":"105000024","stat_value":230},{"stat_id":"105000029","stat_value":937},{"stat_id":"105000102","stat_value":2.26},{"stat_id":"105000105","stat_value":1.88}]},{"level":28,"stat_detail":[{"stat_id":"105000001","stat_value":490},{"stat_id":"105000025","stat_value":244},{"stat_id":"105000024","stat_value":234},{"stat_id":"105000029","stat_value":993},{"stat_id":"105000102","stat_value":2.4},{"stat_id":"105000105","stat_value":2}]},{"level":29,"stat_detail":[{"stat_id":"105000001","stat_value":513},{"stat_id":"105000025","stat_value":255},{"stat_id":"105000024","stat_value":239},{"stat_id":"105000029","stat_value":1049},{"stat_id":"105000102","stat_value":2.5},{"stat_id":"105000105","stat_value":2.08}]},{"level":30,"stat_detail":[{"stat_id":"105000001","stat_value":536},{"stat_id":"105000025","stat_value":266},{"stat_id":"105000024","stat_value":243},{"stat_id":"105000029","stat_value":1107},{"stat_id":"105000102","stat_value":2.64},{"stat_id":"105000105","stat_value":2.2}]},{"level":31,"stat_detail":[{"stat_id":"105000001","stat_value":564},{"stat_id":"105000025","stat_value":281},{"stat_id":"105000024","stat_value":247},{"stat_id":"105000029","stat_value":1166},{"stat_id":"105000102","stat_value":2.76},{"stat_id":"105000105","stat_value":2.3}]},{"level":32,"stat_detail":[{"stat_id":"105000001","stat_value":587},{"stat_id":"105000025","stat_value":292},{"stat_id":"105000024","stat_value":253},{"stat_id":"105000029","stat_value":1227},{"stat_id":"105000102","stat_value":2.88},{"stat_id":"105000105","stat_value":2.4}]},{"level":33,"stat_detail":[{"stat_id":"105000001","stat_value":616},{"stat_id":"105000025","stat_value":307},{"stat_id":"105000024","stat_value":259},{"stat_id":"105000029","stat_value":1288},{"stat_id":"105000102","stat_value":3},{"stat_id":"105000105","stat_value":2.5}]},{"level":34,"stat_detail":[{"stat_id":"105000001","stat_value":641},{"stat_id":"105000025","stat_value":320},{"stat_id":"105000024","stat_value":265},{"stat_id":"105000029","stat_value":1353},{"stat_id":"105000102","stat_value":3.14},{"stat_id":"105000105","stat_value":2.62}]},{"level":35,"stat_detail":[{"stat_id":"105000001","stat_value":670},{"stat_id":"105000025","stat_value":333},{"stat_id":"105000024","stat_value":271},{"stat_id":"105000029","stat_value":1418},{"stat_id":"105000102","stat_value":3.26},{"stat_id":"105000105","stat_value":2.72}]},{"level":36,"stat_detail":[{"stat_id":"105000001","stat_value":696},{"stat_id":"105000025","stat_value":346},{"stat_id":"105000024","stat_value":276},{"stat_id":"105000029","stat_value":1484},{"stat_id":"105000102","stat_value":3.41},{"stat_id":"105000105","stat_value":2.84}]},{"level":37,"stat_detail":[{"stat_id":"105000001","stat_value":724},{"stat_id":"105000025","stat_value":361},{"stat_id":"105000024","stat_value":282},{"stat_id":"105000029","stat_value":1553},{"stat_id":"105000102","stat_value":3.53},{"stat_id":"105000105","stat_value":2.94}]},{"level":38,"stat_detail":[{"stat_id":"105000001","stat_value":753},{"stat_id":"105000025","stat_value":375},{"stat_id":"105000024","stat_value":288},{"stat_id":"105000029","stat_value":1622},{"stat_id":"105000102","stat_value":3.67},{"stat_id":"105000105","stat_value":3.06}]},{"level":39,"stat_detail":[{"stat_id":"105000001","stat_value":782},{"stat_id":"105000025","stat_value":390},{"stat_id":"105000024","stat_value":294},{"stat_id":"105000029","stat_value":1695},{"stat_id":"105000102","stat_value":3.82},{"stat_id":"105000105","stat_value":3.18}]},{"level":40,"stat_detail":[{"stat_id":"105000001","stat_value":810},{"stat_id":"105000025","stat_value":404},{"stat_id":"105000024","stat_value":300},{"stat_id":"105000029","stat_value":1767},{"stat_id":"105000102","stat_value":3.96},{"stat_id":"105000105","stat_value":3.3}]}],"descendant_skill":[{"skill_type":"액티브 스킬","skill_name":"짜릿탄","element_type":"전기","arche_type":"융합","skill_image_url":"https://open.api.nexon.com/static/tfd/img/1f3e0ff139868e2776021a08ef88c5d9","skill_description":"짜릿탄을 생성해 범위 내 가장 가까운 적에게 피해를 입히며 전기력 보유량에 비례하여 피해량이 증가합니다.\n피격된 적에게 감전 효과를 부여합니다."},{"skill_type":"액티브 스킬","skill_name":"광속 질주","element_type":"전기","arche_type":"특이","skill_image_url":"https://open.api.nexon.com/static/tfd/img/f799da1ae38071c8911d37d1a20be04f","skill_description":"항상 전력 질주로 이동하게 되고 전력 질주 속도가 증가합니다.\n광속 질주 효과를 얻습니다. 광속 질주는 이동 중 추가로 전기력을 획득합니다."},{"skill_type":"액티브 스킬","skill_name":"번개 방출","element_type":"전기","arche_type":"특이","skill_image_url":"https://open.api.nexon.com/static/tfd/img/bdd0dd077be2e914d946827d0fa500b1","skill_description":"번개 방출 상태가 됩니다. 일정거리를 이동 할 때마다 주변 적에게 피해를 입히며 전기력 보유량에 비례하여 피해량이 증가합니다. 피격된 적에게 감전 효과를 부여합니다."},{"skill_type":"액티브 스킬","skill_name":"최대 출력","element_type":"전기","arche_type":"융합","skill_image_url":"https://open.api.nexon.com/static/tfd/img/92b2d76455a44da169836c3e2e6033ca","skill_description":"전방으로 전기를 방출합니다. 방출한 전기에 닿은 적에게 피해를 입히며, 방출한 시간에 따라 피해가 점진적으로 증가합니다. 전기력을 모두 소모하면 종료됩니다."},{"skill_type":"패시브 스킬","skill_name":"날쌘 토끼","element_type":"전기","arche_type":"융합","skill_image_url":"https://open.api.nexon.com/static/tfd/img/23f51e4cda9aaf5625e85e11e847111d","skill_description":"2단 점프 후 착지하면 주변 적에게 피해를 입힙니다.\n이동 거리에 비례하여 전기력을 획득합니다.\n일정시간 동안 이동이 없으면 전기력을 점진적으로 소모합니다."}],"detail":{"descendant_id":"101000019","eng_name":"ULT BUNNY","tier":"ult","role":"지속 딜러","point":"얼티밋 프로젝트를 통해 강한 힘을 얻게 된 버니.\n달리면 달릴수록 전기 에너지가 쌓이며, 이를 방출하여 적을 공격할 수 있다.","attribute":"electric","story":"얼티밋 계승자 프로젝트는 잉그리스 곳곳에서 발견되고 있는 선각자들의 기술과 장비, 혹은 특수 아르케 유전자를 현역 계승자들의 특성에 맞게 개량하고 적용하는 계획을 의미한다. 궁극적인 목표는, 모든 계승자들을 강력했던 인류의 선대, 선각자의 모습으로 강화 시키는 것. 그리고 이 계획이 계승자들에게 공표되자, 버니는 자신이 낼 수 있는 최대 속력으로 매지스터들에게 달려갔다.\n\n“선착순, 맞지?”\n\n물론, 얼티밋 프로젝트에 선착순 같은 것은 없었다. 더욱이 얼티밋 기술의 첫 대상자는 이미 레픽으로 선정된 상황. 그렇게 잔뜩 김빠진 표정으로 연구실을 나가려는 찰나, 버니는 연구실 한 켠에 놓여있던 정체불명의 장비들을 발견했다. 그것은 얼마전 매지스터들이 복원해낸 어떤 얼티밋 장비의 구성품으로, 본래 전신을 감싸는 스킨 슈트로 추정되는 물건이었지만, 더 이상 자료를 찾지 못해 복원을 중단했던 비운의 부품들이었다.\n\n하지만 이 부품들은 어지간한 완성품 못지 않은 위력을 지니고 있었다. 먼저 아르케로 구동되는 장갑 부츠는, 미세 진동으로 근막 수축 이완을 도와 사용자의 기동력을 한계까지 끌어올릴 수 있었다. 전용 헬멧은 이렇게 한계 속도 상태의 사용자에게 흡수 효율이 높은 산소를 제공하여 고속 기동을 장시간 운용할 수 있게끔 보조했으며, 헬멧에 부착된 바이저는 에시브와도 실시간 연동되어 다양한 전장 정보까지 제공할 수 있었다.\n\n단점이라면, 슈트 부분이 완벽히 복원되지 않아 곳곳이 훤히 드러났다는 점. 하지만 방어력 따위는 애당초 맞지 않으면 상관없는 일이었으며, 이렇게 극단적인 경량화야 말로 ‘버니’에게 딱 맞는 얼티밋 장비의 모습이었다.\n\n어떻게 확신할 수 있냐고?\n\n그새 장비를 훔쳐 갈아입고, 빛의 속도로 달리고 있는 버니의 뒷모습을 보라.\n비록 매지스터들은 선각자들이 남긴 귀중한 물품을 도둑 맞았지만, 그 순간 또 하나의 얼티밋 계승자 프로젝트가 성공한 셈이니 모두가 행복했을 것이다…","only_weapon":"얼티밋 장비, 초경량화 운동성 강화복 \"하얀 토끼\"","only_weapon_desc":"이 얼티밋 장비는 당초 버니를 위한 것이 아니었지만, 버니가 실행한 뜻밖의 ‘실전 테스트‘ 덕분에 장비의 진면목이 드러났다고 볼 수 있다. 장갑 부츠의 미세 진동은 버니가 내뿜는 생체 전류 덕분에 더 강력한 성능과 속도 증진을 선보였고, 이를 통해 더욱 많은 전류를 생성해낸 버니는 기존보다 몇 배는 강력한 아르케 능력을 발휘할 수 있었다. 유일한 단점이라면, 얼티밋 장비 특유의 희귀 원소가 모색을 하얗게 물들인다는 것이다.","only_weapon_comment":"\"뭐 어때? 하얀 토끼 같고, 좋지 않아?\"\n- 버니"},"descendant_passive_skill":{"skill_type":"패시브 스킬","skill_name":"날쌘 토끼","element_type":"전기","arche_type":"융합","skill_image_url":"https://open.api.nexon.com/static/tfd/img/23f51e4cda9aaf5625e85e11e847111d","skill_description":"2단 점프 후 착지하면 주변 적에게 피해를 입힙니다.\n이동 거리에 비례하여 전기력을 획득합니다.\n일정시간 동안 이동이 없으면 전기력을 점진적으로 소모합니다."}}