{"weapon_id":"211042002","weapon_name":"꽃피우는 혈통","image_url":"https://open.api.nexon.com/static/tfd/img/bd3db3617859fab6dc91f200d74ca5a4","weapon_type":"기관단총","weapon_tier_id":"Tier2","weapon_rounds_type":"일반탄","available_core_slot":[],"base_stat":[{"stat_id":"105000023","stat_value":1000},{"stat_id":"105000035","stat_value":1},{"stat_id":"105000077","stat_value":1},{"stat_id":"105000054","stat_value":20},{"stat_id":"105000055","stat_value":40},{"stat_id":"105000056","stat_value":0.3},{"stat_id":"105000005","stat_value":150},{"stat_id":"105000006","stat_value":77.77},{"stat_id":"105000036","stat_value":87.33},{"stat_id":"105000051","stat_value":3},{"stat_id":"105000007","stat_value":31},{"stat_id":"105000037","stat_value":4.2},{"stat_id":"105000038","stat_value":1.2},{"stat_id":"105000039","stat_value":1.21},{"stat_id":"105000040","stat_value":17},{"stat_id":"105000041","stat_value":36},{"stat_id":"105000021","stat_value":27},{"stat_id":"105000022","stat_value":27},{"stat_id":"105000095","stat_value":1.32},{"stat_id":"105000033","stat_value":-1},{"stat_id":"105000019","stat_value":800},{"stat_id":"105000018","stat_value":540},{"stat_id":"105000034","stat_value":540},{"stat_id":"105000020","stat_value":540},{"stat_id":"105000069","stat_value":10},{"stat_id":"105000008","stat_value":100},{"stat_id":"105000092","stat_value":2},{"stat_id":"105000030","stat_value":12},{"stat_id":"105000031","stat_value":1.5},{"stat_id":"105000170","stat_value":3.7},{"stat_id":"105000229","stat_value":0.38}],"firearm_atk":[{"level":1,"firearm":[{"firearm_atk_type":"105000026","firearm_atk_value":24}]},{"level":2,"firearm":[{"firearm_atk_type":"105000026","firearm_atk_value":52}]},{"level":3,"firearm":[{"firearm_atk_type":"105000026","firearm_atk_value":73}]},{"level":4,"firearm":[{"firearm_atk_type":"105000026","firearm_atk_value":97}]},{"level":5,"firearm":[{"firearm_atk_type":"105000026","firearm_atk_value":124}]},{"level":6,"firearm":[{"firearm_atk_type":"105000026","firearm_atk_value":154}]},{"level":7,"firearm":[{"firearm_atk_type":"105000026","firearm_atk_value":185}]},{"level":8,"firearm":[{"firearm_atk_type":"105000026","firearm_atk_value":219}]},{"level":9,"firearm":[{"firearm_atk_type":"105000026","firearm_atk_value":256}]},{"level":10,"firearm":[{"firearm_atk_type":"105000026","firearm_atk_value":294}]},{"level":11,"firearm":[{"firearm_atk_type":"105000026","firearm_atk_value":334}]},{"level":12,"firearm":[{"firearm_atk_type":"105000026","firearm_atk_value":376}]},{"level":13,"firearm":[{"firearm_atk_type":"105000026","firearm_atk_value":420}]},{"level":14,"firearm":[{"firearm_atk_type":"105000026","firearm_atk_value":460}]},{"level":15,"firearm":[{"firearm_atk_type":"105000026","firearm_atk_value":501}]},{"level":16,"firearm":[{"firearm_atk_type":"105000026","firearm_atk_value":538}]},{"level":17,"firearm":[{"firearm_atk_type":"105000026","firearm_atk_value":574}]},{"level":18,"firearm":[{"firearm_atk_type":"105000026","firearm_atk_value":609}]},{"level":19,"firearm":[{"firearm_atk_type":"105000026","firearm_atk_value":653}]},{"level":20,"firearm":[{"firearm_atk_type":"105000026","firearm_atk_value":698}]},{"level":21,"firearm":[{"firearm_atk_type":"105000026","firearm_atk_value":750}]},{"level":22,"firearm":[{"firearm_atk_type":"105000026","firearm_atk_value":807}]},{"level":23,"firearm":[{"firearm_atk_type":"105000026","firearm_atk_value":866}]},{"level":24,"firearm":[{"firearm_atk_type":"105000026","firearm_atk_value":927}]},{"level":25,"firearm":[{"firearm_atk_type":"105000026","firearm_atk_value":990}]},{"level":26,"firearm":[{"firearm_atk_type":"105000026","firearm_atk_value":1055}]},{"level":27,"firearm":[{"firearm_atk_type":"105000026","firearm_atk_value":1122}]},{"level":28,"firearm":[{"firearm_atk_type":"105000026","firearm_atk_value":1191}]},{"level":29,"firearm":[{"firearm_atk_type":"105000026","firearm_atk_value":1262}]},{"level":30,"firearm":[{"firearm_atk_type":"105000026","firearm_atk_value":1335}]},{"level":31,"firearm":[{"firearm_atk_type":"105000026","firearm_atk_value":1410}]},{"level":32,"firearm":[{"firearm_atk_type":"105000026","firearm_atk_value":1487}]},{"level":33,"firearm":[{"firearm_atk_type":"105000026","firearm_atk_value":1566}]},{"level":34,"firearm":[{"firearm_atk_type":"105000026","firearm_atk_value":1647}]},{"level":35,"firearm":[{"firearm_atk_type":"105000026","firearm_atk_value":1730}]},{"level":36,"firearm":[{"firearm_atk_type":"105000026","firearm_atk_value":1815}]},{"level":37,"firearm":[{"firearm_atk_type":"105000026","firearm_atk_value":1902}]},{"level":38,"firearm":[{"firearm_atk_type":"105000026","firearm_atk_value":1991}]},{"level":39,"firearm":[{"firearm_atk_type":"105000026","firearm_atk_value":2082}]},{"level":40,"firearm":[{"firearm_atk_type":"105000026","firearm_atk_value":2175}]},{"level":41,"firearm":[{"firearm_atk_type":"105000026","firearm_atk_value":2270}]},{"level":42,"firearm":[{"firearm_atk_type":"105000026","firearm_atk_value":2367}]},{"level":43,"firearm":[{"firearm_atk_type":"105000026","firearm_atk_value":2466}]},{"level":44,"firearm":[{"firearm_atk_type":"105000026","firearm_atk_value":2567}]},{"level":45,"firearm":[{"firearm_atk_type":"105000026","firearm_atk_value":2669}]},{"level":46,"firearm":[{"firearm_atk_type":"105000026","firearm_atk_value":2774}]},{"level":47,"firearm":[{"firearm_atk_type":"105000026","firearm_atk_value":2881}]},{"level":48,"firearm":[{"firearm_atk_type":"105000026","firearm_atk_value":2990}]},{"level":49,"firearm":[{"firearm_atk_type":"105000026","firearm_atk_value":3101}]},{"level":50,"firearm":[{"firearm_atk_type":"105000026","firearm_atk_value":3214}]},{"level":51,"firearm":[{"firearm_atk_type":"105000026","firearm_atk_value":3329}]},{"level":52,"firearm":[{"firearm_atk_type":"105000026","firearm_atk_value":3446}]},{"level":53,"firearm":[{"firearm_atk_type":"105000026","firearm_atk_value":3565}]},{"level":54,"firearm":[{"firearm_atk_type":"105000026","firearm_atk_value":3686}]},{"level":55,"firearm":[{"firearm_atk_type":"105000026","firearm_atk_value":3809}]},{"level":56,"firearm":[{"firearm_atk_type":"105000026","firearm_atk_value":3934}]},{"level":57,"firearm":[{"firearm_atk_type":"105000026","firearm_atk_value":4061}]},{"level":58,"firearm":[{"firearm_atk_type":"105000026","firearm_atk_value":4190}]},{"level":59,"firearm":[{"firearm_atk_type":"105000026","firearm_atk_value":4320}]},{"level":60,"firearm":[{"firearm_atk_type":"105000026","firearm_atk_value":4453}]},{"level":61,"firearm":[{"firearm_atk_type":"105000026","firearm_atk_value":4588}]},{"level":62,"firearm":[{"firearm_atk_type":"105000026","firearm_atk_value":4725}]},{"level":63,"firearm":[{"firearm_atk_type":"105000026","firearm_atk_value":4864}]},{"level":64,"firearm":[{"firearm_atk_type":"105000026","firearm_atk_value":5005}]},{"level":65,"firearm":[{"firearm_atk_type":"105000026","firearm_atk_value":5148}]},{"level":66,"firearm":[{"firearm_atk_type":"105000026","firearm_atk_value":5293}]},{"level":67,"firearm":[{"firearm_atk_type":"105000026","firearm_atk_value":5440}]},{"level":68,"firearm":[{"firearm_atk_type":"105000026","firearm_atk_value":5589}]},{"level":69,"firearm":[{"firearm_atk_type":"105000026","firearm_atk_value":5739}]},{"level":70,"firearm":[{"firearm_atk_type":"105000026","firearm_atk_value":5892}]},{"level":71,"firearm":[{"firearm_atk_type":"105000026","firearm_atk_value":6047}]},{"level":72,"firearm":[{"firearm_atk_type":"105000026","firearm_atk_value":6204}]},{"level":73,"firearm":[{"firearm_atk_type":"105000026","firearm_atk_value":6363}]},{"level":74,"firearm":[{"firearm_atk_type":"105000026","firearm_atk_value":6524}]},{"level":75,"firearm":[{"firearm_atk_type":"105000026","firearm_atk_value":6687}]},{"level":76,"firearm":[{"firearm_atk_type":"105000026","firearm_atk_value":6852}]},{"level":77,"firearm":[{"firearm_atk_type":"105000026","firearm_atk_value":7018}]},{"level":78,"firearm":[{"firearm_atk_type":"105000026","firearm_atk_value":7187}]},{"level":79,"firearm":[{"firearm_atk_type":"105000026","firearm_atk_value":7358}]},{"level":80,"firearm":[{"firearm_atk_type":"105000026","firearm_atk_value":7531}]},{"level":81,"firearm":[{"firearm_atk_type":"105000026","firearm_atk_value":7706}]},{"level":82,"firearm":[{"firearm_atk_type":"105000026","firearm_atk_value":7883}]},{"level":83,"firearm":[{"firearm_atk_type":"105000026","firearm_atk_value":8062}]},{"level":84,"firearm":[{"firearm_atk_type":"105000026","firearm_atk_value":8242}]},{"level":85,"firearm":[{"firearm_atk_type":"105000026","firearm_atk_value":8425}]},{"level":86,"firearm":[{"firearm_atk_type":"105000026","firearm_atk_value":8610}]},{"level":87,"firearm":[{"firearm_atk_type":"105000026","firearm_atk_value":8797}]},{"level":88,"firearm":[{"firearm_atk_type":"105000026","firearm_atk_value":8986}]},{"level":89,"firearm":[{"firearm_atk_type":"105000026","firearm_atk_value":9177}]},{"level":90,"firearm":[{"firearm_atk_type":"105000026","firearm_atk_value":9370}]},{"level":91,"firearm":[{"firearm_atk_type":"105000026","firearm_atk_value":9564}]},{"level":92,"firearm":[{"firearm_atk_type":"105000026","firearm_atk_value":9761}]},{"level":93,"firearm":[{"firearm_atk_type":"105000026","firearm_atk_value":9960}]},{"level":94,"firearm":[{"firearm_atk_type":"105000026","firearm_atk_value":10161}]},{"level":95,"firearm":[{"firearm_atk_type":"105000026","firearm_atk_value":10364}]},{"level":96,"firearm":[{"firearm_atk_type":"105000026","firearm_atk_value":10569}]},{"level":97,"firearm":[{"firearm_atk_type":"105000026","firearm_atk_value":10775}]},{"level":98,"firearm":[{"firearm_atk_type":"105000026","firearm_atk_value":10984}]},{"level":99,"firearm":[{"firearm_atk_type":"105000026","firearm_atk_value":11195}]},{"level":100,"firearm":[{"firearm_atk_type":"105000026","firearm_atk_value":11408}]},{"level":101,"firearm":[{"firearm_atk_type":"105000026","firearm_atk_value":11623}]},{"level":102,"firearm":[{"firearm_atk_type":"105000026","firearm_atk_value":11839}]},{"level":103,"firearm":[{"firearm_atk_type":"105000026","firearm_atk_value":12058}]},{"level":104,"firearm":[{"firearm_atk_type":"105000026","firearm_atk_value":12279}]},{"level":105,"firearm":[{"firearm_atk_type":"105000026","firearm_atk_value":12502}]},{"level":106,"firearm":[{"firearm_atk_type":"105000026","firearm_atk_value":12727}]},{"level":107,"firearm":[{"firearm_atk_type":"105000026","firearm_atk_value":12953}]},{"level":108,"firearm":[{"firearm_atk_type":"105000026","firearm_atk_value":13182}]},{"level":109,"firearm":[{"firearm_atk_type":"105000026","firearm_atk_value":13413}]},{"level":110,"firearm":[{"firearm_atk_type":"105000026","firearm_atk_value":13646}]},{"level":111,"firearm":[{"firearm_atk_type":"105000026","firearm_atk_value":13881}]},{"level":112,"firearm":[{"firearm_atk_type":"105000026","firearm_atk_value":14117}]},{"level":113,"firearm":[{"firearm_atk_type":"105000026","firearm_atk_value":14356}]},{"level":114,"firearm":[{"firearm_atk_type":"105000026","firearm_atk_value":14597}]},{"level":115,"firearm":[{"firearm_atk_type":"105000026","firearm_atk_value":14840}]},{"level":116,"firearm":[{"firearm_atk_type":"105000026","firearm_atk_value":15085}]},{"level":117,"firearm":[{"firearm_atk_type":"105000026","firearm_atk_value":15331}]},{"level":118,"firearm":[{"firearm_atk_type":"105000026","firearm_atk_value":15580}]},{"level":119,"firearm":[{"firearm_atk_type":"105000026","firearm_atk_value":15831}]},{"level":120,"firearm":[{"firearm_atk_type":"105000026","firearm_atk_value":16084}]},{"level":121,"firearm":[{"firearm_atk_type":"105000026","firearm_atk_value":16339}]},{"level":122,"firearm":[{"firearm_atk_type":"105000026","firearm_atk_value":16595}]},{"level":123,"firearm":[{"firearm_atk_type":"105000026","firearm_atk_value":16854}]},{"level":124,"firearm":[{"firearm_atk_type":"105000026","firearm_atk_value":17115}]},{"level":125,"firearm":[{"firearm_atk_type":"105000026","firearm_atk_value":17378}]},{"level":126,"firearm":[{"firearm_atk_type":"105000026","firearm_atk_value":17642}]},{"level":127,"firearm":[{"firearm_atk_type":"105000026","firearm_atk_value":17909}]},{"level":128,"firearm":[{"firearm_atk_type":"105000026","firearm_atk_value":18178}]},{"level":129,"firearm":[{"firearm_atk_type":"105000026","firearm_atk_value":18449}]},{"level":130,"firearm":[{"firearm_atk_type":"105000026","firearm_atk_value":18721}]},{"level":131,"firearm":[{"firearm_atk_type":"105000026","firearm_atk_value":18996}]},{"level":132,"firearm":[{"firearm_atk_type":"105000026","firearm_atk_value":19273}]},{"level":133,"firearm":[{"firearm_atk_type":"105000026","firearm_atk_value":19552}]},{"level":134,"firearm":[{"firearm_atk_type":"105000026","firearm_atk_value":19832}]},{"level":135,"firearm":[{"firearm_atk_type":"105000026","firearm_atk_value":20115}]},{"level":136,"firearm":[{"firearm_atk_type":"105000026","firearm_atk_value":20400}]},{"level":137,"firearm":[{"firearm_atk_type":"105000026","firearm_atk_value":20687}]},{"level":138,"firearm":[{"firearm_atk_type":"105000026","firearm_atk_value":20975}]},{"level":139,"firearm":[{"firearm_atk_type":"105000026","firearm_atk_value":21266}]},{"level":140,"firearm":[{"firearm_atk_type":"105000026","firearm_atk_value":21559}]},{"level":141,"firearm":[{"firearm_atk_type":"105000026","firearm_atk_value":21853}]},{"level":142,"firearm":[{"firearm_atk_type":"105000026","firearm_atk_value":22150}]},{"level":143,"firearm":[{"firearm_atk_type":"105000026","firearm_atk_value":22449}]},{"level":144,"firearm":[{"firearm_atk_type":"105000026","firearm_atk_value":22750}]},{"level":145,"firearm":[{"firearm_atk_type":"105000026","firearm_atk_value":23052}]},{"level":146,"firearm":[{"firearm_atk_type":"105000026","firearm_atk_value":23357}]},{"level":147,"firearm":[{"firearm_atk_type":"105000026","firearm_atk_value":23664}]},{"level":148,"firearm":[{"firearm_atk_type":"105000026","firearm_atk_value":23973}]},{"level":149,"firearm":[{"firearm_atk_type":"105000026","firearm_atk_value":24283}]},{"level":150,"firearm":[{"firearm_atk_type":"105000026","firearm_atk_value":24596}]},{"level":151,"firearm":[{"firearm_atk_type":"105000026","firearm_atk_value":24911}]},{"level":152,"firearm":[{"firearm_atk_type":"105000026","firearm_atk_value":25227}]},{"level":153,"firearm":[{"firearm_atk_type":"105000026","firearm_atk_value":25546}]},{"level":154,"firearm":[{"firearm_atk_type":"105000026","firearm_atk_value":25867}]},{"level":155,"firearm":[{"firearm_atk_type":"105000026","firearm_atk_value":26189}]},{"level":156,"firearm":[{"firearm_atk_type":"105000026","firearm_atk_value":26514}]},{"level":157,"firearm":[{"firearm_atk_type":"105000026","firearm_atk_value":26841}]},{"level":158,"firearm":[{"firearm_atk_type":"105000026","firearm_atk_value":27170}]},{"level":159,"firearm":[{"firearm_atk_type":"105000026","firearm_atk_value":27500}]},{"level":160,"firearm":[{"firearm_atk_type":"105000026","firearm_atk_value":27833}]}],"weapon_perk_ability_name":null,"weapon_perk_ability_description":null,"weapon_perk_ability_image_url":null}